[

    {
        "count":"1" ,
        "id":"bigNavbar" ,
        "title":"محصولات",
        "more":true ,
        "angleIconBlack":"icons/navBar/angle-down-black.svg",
        "angleIconWhite":"icons/navBar/angle-down-white.svg" ,
        "menuClass":1 , 
        "moreTitlesRight":[

            {
                "productTitle":"درگاه پرداخت" ,
                "productSubtitle":"مهندسی شده برای فروش بیش‌تر"
            },

            {
                "productTitle":"عیان" ,
                "productSubtitle":"احراز هویت واقعی خریدار"
            },

            {   
                "productTitle":"زرین‌لینک" ,
                "productSubtitle":"لینک پرداخت در شبکه‌های اجتماعی"
            },

            {
                "productTitle":"زرین‌پلاس" ,
                "productSubtitle":"ابزار هوشمند سوددهی"
            }

        ] , 
        "moreTitlesLeft":[

            {
                "productTitle":"زرین‌کارت" ,
                "productSubtitle":"طلایی‌ترین کارتِ بانکی"
            },

            {
                "productTitle":"استرداد وجه" ,
                "productSubtitle":"مبلغ تراکنش را در لحظه برگشت بزنید"
            },

            {
                "productTitle":"تسویه پیش از موعد" ,
                "productSubtitle":"دریافت موجودی قابل تسویه در سریع‌ترین زمان"
            },

            {
                "productTitle":"تسهیم فردایی" ,
                "productSubtitle":"تقسیم و واریز مبلغ به شرکای تجاری"
            }
        ]
    },

    {
        "count":"2" ,
        "id":"bigNavbar" ,
        "title":"تعرفه‌ها",
        "more":false
    },

    {
        "count":"3" ,
        "id":"bigNavbar" ,
        "title":"توسعه‌دهندگان",
        "more":false
    },

    {
        "count":"4" ,
        "id":"bigNavbar" ,
        "title":"تماس با ما",
        "more":false
    },

    {
        "count":"5" ,
        "id":"bigNavbar" , 
        "title":"بیش‌تر",
        "more":true ,
        "angleIconBlack":"icons/navBar/angle-down-black.svg",
        "angleIconWhite":"icons/navBar/angle-down-white.svg" ,
        "menuClass": 2 , 
        "moreTitles":[
            {"productTitle":"وبلاگ"},
            {"productTitle":"دریافت شماره شبا"},
            {"productTitle":"سوالات متداول"},
            {"productTitle":"اپلیکیشن"},
            {"productTitle":"زرین‌بین"}
        ]
    },

    {
        "count":"6" ,
        "id":"bigNavbar" ,
        "title":"زرین‌پال من",
        "more":false ,
        "button":true
    }
    
]